jzpack/__init__.py
jzpack/analyzer.py
jzpack/compressor.py
jzpack/encoders.py
jzpack/py.typed
jzpack/schema.py
jzpack/serializer.py
jzpack-0.2.0.dist-info/METADATA
jzpack-0.2.0.dist-info/WHEEL
jzpack-0.2.0.dist-info/licenses/LICENSE
jzpack-0.2.0.dist-info/RECORD
