Metadata-Version: 2.4
Name: jzpack
Version: 0.2.0
Summary: High-performance JSON/NDJSON compression library
Project-URL: Homepage, https://github.com/hasanzaibak/jzpack
Project-URL: Repository, https://github.com/hasanzaibak/jzpack
Project-URL: Issues, https://github.com/hasanzaibak/jzpack/issues
Author: hasanzaibak
License: MIT
License-File: LICENSE
Keywords: compression,json,logs,msgpack,ndjson,zstd
Classifier: Development Status :: 4 - Beta
Classifier: Intended Audience :: Developers
Classifier: License :: OSI Approved :: MIT License
Classifier: Operating System :: OS Independent
Classifier: Programming Language :: Python :: 3
Classifier: Programming Language :: Python :: 3.10
Classifier: Programming Language :: Python :: 3.11
Classifier: Programming Language :: Python :: 3.12
Classifier: Programming Language :: Python :: 3.13
Classifier: Topic :: System :: Archiving :: Compression
Classifier: Typing :: Typed
Requires-Python: >=3.10
Requires-Dist: msgpack>=1.0.0
Requires-Dist: zstandard>=0.21.0
Provides-Extra: dev
Requires-Dist: black<26.0.0,>=25.12.0; extra == 'dev'
Requires-Dist: isort<8.0.0,>=7.0.0; extra == 'dev'
Requires-Dist: pytest>=7.0.0; extra == 'dev'
